[
  [
    "stormy sea",
    "",
    "",
    "n",
    0,
    [
      {
        "type": "structured-content",
        "content": [
          {
            "tag": "div",
            "content": [
              {
                "tag": "div",
                "data": {
                  "content": "preamble"
                },
                "content": [
                  {
                    "tag": "details",
                    "data": {
                      "content": "details-entry-Etymology"
                    },
                    "content": [
                      {
                        "tag": "summary",
                        "data": {
                          "content": "summary-entry"
                        },
                        "content": "Etymology"
                      },
                      {
                        "tag": "div",
                        "data": {
                          "content": "Etymology-content"
                        },
                        "content": "Nghĩa đen chỉ những vùng biển có thời tiết xấu, gió mạnh, sóng to và biển động rất nguy hiểm. Nghĩa bóng dùng để mô tả những tình huống khó khăn, thử thách, hoặc giai đoạn khó khăn trong cuộc sống, giống như việc phải vượt qua những cơn bão dữ ngoài biển khơi."
                      }
                    ]
                  }
                ]
              }
            ]
          },
          {
            "tag": "ol",
            "data": {
              "content": "glosses"
            },
            "content": [
              {
                "tag": "li",
                "content": [
                  {
                    "tag": "div",
                    "content": [
                      "biển động dữ dội, bão trên biển"
                    ]
                  },
                  {
                    "tag": "div",
                    "content": [
                      {
                        "tag": "details",
                        "data": {
                          "content": "details-entry-examples"
                        },
                        "content": [
                          {
                            "tag": "summary",
                            "data": {
                              "content": "summary-entry"
                            },
                            "content": "1 examples"
                          },
                          {
                            "tag": "div",
                            "data": {
                              "content": "extra-info"
                            },
                            "content": {
                              "tag": "div",
                              "data": {
                                "content": "example-sentence"
                              },
                              "content": [
                                {
                                  "tag": "div",
                                  "data": {
                                    "content": "example-sentence-a"
                                  },
                                  "content": "in stormy seas"
                                },
                                {
                                  "tag": "div",
                                  "data": {
                                    "content": "example-sentence-b"
                                  },
                                  "content": ""
                                }
                              ]
                            }
                          }
                        ]
                      }
                    ]
                  }
                ]
              }
            ]
          },
          {
            "tag": "div",
            "data": {
              "content": "backlink"
            },
            "content": [
              {
                "tag": "a",
                "href": "https://vi.wiktionary.org/wiki/stormy%20sea#English",
                "content": "Wiktionary"
              }
            ]
          }
        ]
      }
    ],
    0,
    ""
  ],
  [
    "stepwell",
    "",
    "",
    "n",
    0,
    [
      {
        "type": "structured-content",
        "content": [
          {
            "tag": "div",
            "content": [
              {
                "tag": "div",
                "data": {
                  "content": "preamble"
                },
                "content": [
                  {
                    "tag": "details",
                    "data": {
                      "content": "details-entry-Etymology"
                    },
                    "content": [
                      {
                        "tag": "summary",
                        "data": {
                          "content": "summary-entry"
                        },
                        "content": "Etymology"
                      },
                      {
                        "tag": "div",
                        "data": {
                          "content": "Etymology-content"
                        },
                        "content": "giếng nước hoặc bể nước có cầu thang dài dẫn xuống mực nước, phổ biến ở miền Tây Ấn Độ từ thế kỷ 7 đến thế kỷ 19. Chúng được thiết kế để khai thác nước ngầm ổn định quanh năm trong những vùng khí hậu khô cằn. Các bước thang dẫn xuống lòng đất giúp tiếp cận mực nước thay đổi theo mùa mưa và hạn hán. Ngoài chức năng cấp nước cho sinh hoạt, rửa ráy, tưới tiêu, stepwells còn tạo ra không gian mát mẻ, yên tĩnh tránh nóng cho người qua lại."
                      }
                    ]
                  }
                ]
              }
            ]
          },
          {
            "tag": "ol",
            "data": {
              "content": "glosses"
            },
            "content": [
              {
                "tag": "li",
                "content": [
                  {
                    "tag": "div",
                    "content": [
                      "giếng bậc thang"
                    ]
                  }
                ]
              }
            ]
          },
          {
            "tag": "div",
            "data": {
              "content": "backlink"
            },
            "content": [
              {
                "tag": "a",
                "href": "https://vi.wiktionary.org/wiki/stepwell#English",
                "content": "Wiktionary"
              }
            ]
          }
        ]
      }
    ],
    0,
    ""
  ],
  [
    "utilitarian",
    "",
    "",
    "adj",
    0,
    [
      {
        "type": "structured-content",
        "content": [
          {
            "tag": "div",
            "content": [
              {
                "tag": "div",
                "data": {
                  "content": "preamble"
                },
                "content": [
                  {
                    "tag": "details",
                    "data": {
                      "content": "details-entry-Etymology"
                    },
                    "content": [
                      {
                        "tag": "summary",
                        "data": {
                          "content": "summary-entry"
                        },
                        "content": "Etymology"
                      },
                      {
                        "tag": "div",
                        "data": {
                          "content": "Etymology-content"
                        },
                        "content": "bắt nguồn từ triết lý chủ nghĩa thực dụng (utilitarianism) nghĩa là sản phẩm hoặc thiết kế utilitarian không nhất thiết phải đẹp, nhưng phải phục vụ tốt mục đích sử dụng, bền bỉ, tiết kiệm và dễ dàng duy trì."
                      }
                    ]
                  }
                ]
              }
            ]
          },
          {
            "tag": "ol",
            "data": {
              "content": "glosses"
            },
            "content": [
              {
                "tag": "li",
                "content": [
                  {
                    "tag": "div",
                    "content": [
                      "thiết thực"
                    ]
                  },
                  {
                    "tag": "div",
                    "content": [
                      {
                        "tag": "details",
                        "data": {
                          "content": "details-entry-examples"
                        },
                        "content": [
                          {
                            "tag": "summary",
                            "data": {
                              "content": "summary-entry"
                            },
                            "content": "1 examples"
                          },
                          {
                            "tag": "div",
                            "data": {
                              "content": "extra-info"
                            },
                            "content": {
                              "tag": "div",
                              "data": {
                                "content": "example-sentence"
                              },
                              "content": [
                                {
                                  "tag": "div",
                                  "data": {
                                    "content": "example-sentence-a"
                                  },
                                  "content": "utillitarian application"
                                },
                                {
                                  "tag": "div",
                                  "data": {
                                    "content": "example-sentence-b"
                                  },
                                  "content": "ứng dụng thiết thực"
                                }
                              ]
                            }
                          }
                        ]
                      }
                    ]
                  }
                ]
              }
            ]
          },
          {
            "tag": "div",
            "data": {
              "content": "backlink"
            },
            "content": [
              {
                "tag": "a",
                "href": "https://vi.wiktionary.org/wiki/utilitarian#English",
                "content": "Wiktionary"
              }
            ]
          }
        ]
      }
    ],
    0,
    ""
  ],
  [
    "irrigation",
    "",
    "",
    "n",
    0,
    [
      {
        "type": "structured-content",
        "content": [
          {
            "tag": "ol",
            "data": {
              "content": "glosses"
            },
            "content": [
              {
                "tag": "li",
                "content": [
                  {
                    "tag": "div",
                    "content": [
                      "tưới tiêu"
                    ]
                  }
                ]
              }
            ]
          },
          {
            "tag": "div",
            "data": {
              "content": "backlink"
            },
            "content": [
              {
                "tag": "a",
                "href": "https://vi.wiktionary.org/wiki/irrigation#English",
                "content": "Wiktionary"
              }
            ]
          }
        ]
      }
    ],
    0,
    ""
  ],
  [
    "suggest﻿",
    "",
    "",
    "v",
    0,
    [
      {
        "type": "structured-content",
        "content": [
          {
            "tag": "ol",
            "data": {
              "content": "glosses"
            },
            "content": [
              {
                "tag": "li",
                "content": [
                  {
                    "tag": "div",
                    "content": [
                      "gợi ý, đề xuất, đưa ra lời khuyên"
                    ]
                  },
                  {
                    "tag": "div",
                    "content": [
                      {
                        "tag": "details",
                        "data": {
                          "content": "details-entry-examples"
                        },
                        "content": [
                          {
                            "tag": "summary",
                            "data": {
                              "content": "summary-entry"
                            },
                            "content": "1 examples"
                          },
                          {
                            "tag": "div",
                            "data": {
                              "content": "extra-info"
                            },
                            "content": {
                              "tag": "div",
                              "data": {
                                "content": "example-sentence"
                              },
                              "content": [
                                {
                                  "tag": "div",
                                  "data": {
                                    "content": "example-sentence-a"
                                  },
                                  "content": "She suggests going to the new restaurant."
                                },
                                {
                                  "tag": "div",
                                  "data": {
                                    "content": "example-sentence-b"
                                  },
                                  "content": ""
                                }
                              ]
                            }
                          }
                        ]
                      }
                    ]
                  }
                ]
              },
              {
                "tag": "li",
                "content": [
                  {
                    "tag": "div",
                    "content": [
                      "chỉ ra hoặc ngụ ý điều gì đó thông qua biểu hiện, dấu hiệu"
                    ]
                  },
                  {
                    "tag": "div",
                    "content": [
                      {
                        "tag": "details",
                        "data": {
                          "content": "details-entry-examples"
                        },
                        "content": [
                          {
                            "tag": "summary",
                            "data": {
                              "content": "summary-entry"
                            },
                            "content": "1 examples"
                          },
                          {
                            "tag": "div",
                            "data": {
                              "content": "extra-info"
                            },
                            "content": {
                              "tag": "div",
                              "data": {
                                "content": "example-sentence"
                              },
                              "content": [
                                {
                                  "tag": "div",
                                  "data": {
                                    "content": "example-sentence-a"
                                  },
                                  "content": "As their name suggests"
                                },
                                {
                                  "tag": "div",
                                  "data": {
                                    "content": "example-sentence-b"
                                  },
                                  "content": "Như tên của chúng cho thấy"
                                }
                              ]
                            }
                          }
                        ]
                      }
                    ]
                  }
                ]
              }
            ]
          },
          {
            "tag": "div",
            "data": {
              "content": "backlink"
            },
            "content": [
              {
                "tag": "a",
                "href": "https://vi.wiktionary.org/wiki/suggest%EF%BB%BF#English",
                "content": "Wiktionary"
              }
            ]
          }
        ]
      }
    ],
    0,
    ""
  ],
  [
    "underground aquifer",
    "",
    "",
    "n",
    0,
    [
      {
        "type": "structured-content",
        "content": [
          {
            "tag": "ol",
            "data": {
              "content": "glosses"
            },
            "content": [
              {
                "tag": "li",
                "content": [
                  {
                    "tag": "div",
                    "content": [
                      "tầng nước ngầm"
                    ]
                  }
                ]
              }
            ]
          },
          {
            "tag": "div",
            "data": {
              "content": "backlink"
            },
            "content": [
              {
                "tag": "a",
                "href": "https://vi.wiktionary.org/wiki/underground%20aquifer#English",
                "content": "Wiktionary"
              }
            ]
          }
        ]
      }
    ],
    0,
    ""
  ],
  [
    "ancient capital",
    "",
    "",
    "n",
    0,
    [
      {
        "type": "structured-content",
        "content": [
          {
            "tag": "ol",
            "data": {
              "content": "glosses"
            },
            "content": [
              {
                "tag": "li",
                "content": [
                  {
                    "tag": "div",
                    "content": [
                      "kinh đô"
                    ]
                  }
                ]
              }
            ]
          },
          {
            "tag": "div",
            "data": {
              "content": "backlink"
            },
            "content": [
              {
                "tag": "a",
                "href": "https://vi.wiktionary.org/wiki/ancient%20capital#English",
                "content": "Wiktionary"
              }
            ]
          }
        ]
      }
    ],
    0,
    ""
  ],
  [
    "industrialise",
    "",
    "",
    "v",
    0,
    [
      {
        "type": "structured-content",
        "content": [
          {
            "tag": "ol",
            "data": {
              "content": "glosses"
            },
            "content": [
              {
                "tag": "li",
                "content": [
                  {
                    "tag": "div",
                    "content": [
                      "công nghiệp hóa"
                    ]
                  }
                ]
              }
            ]
          },
          {
            "tag": "div",
            "data": {
              "content": "backlink"
            },
            "content": [
              {
                "tag": "a",
                "href": "https://vi.wiktionary.org/wiki/industrialise#English",
                "content": "Wiktionary"
              }
            ]
          }
        ]
      }
    ],
    0,
    ""
  ]
]